{
    "0050.TW": {
        "Date": "2026-06-01",
        "High": 106.69999694824219,
        "Threshold": -0.05
    },
    "2330.TW": {
        "Date": "2026-06-01",
        "High": 2415.0,
        "Threshold": -0.05
    },
    "VEA": {
        "Date": "2026-05-29",
        "High": 72.2300033569336,
        "Threshold": -0.05
    },
    "VT": {
        "Date": "2026-06-01",
        "High": 159.1699981689453,
        "Threshold": -0.05
    },
    "^GSPC": {
        "Date": "2026-06-01",
        "High": 7617.66015625,
        "Threshold": -0.05
    }
}